sobek/__init__.py
sobek-0.0.0.dist-info/LICENSE
sobek-0.0.0.dist-info/METADATA
sobek-0.0.0.dist-info/WHEEL
sobek-0.0.0.dist-info/top_level.txt
sobek-0.0.0.dist-info/RECORD
