Metadata-Version: 2.1
Name: sobek
Version: 0.0.0
Summary: Computer vision for JAX
Author-email: Mahmoud Asem <mahmoudasem00@gmail.com>
License: Apache-2.0
Keywords: jax,neural-networks,functional-programming,machine-learning
Classifier: Development Status :: 5 - Production/Stable
Classifier: Environment :: Console
Classifier: Intended Audience :: Science/Research
Classifier: Intended Audience :: Developers
Classifier: License :: OSI Approved :: Apache Software License
Classifier: Operating System :: OS Independent
Classifier: Programming Language :: Python
Classifier: Programming Language :: Python :: 3
Classifier: Topic :: Scientific/Engineering :: Artificial Intelligence
Classifier: Topic :: Software Development :: Libraries :: Python Modules
Requires-Python: >=3.8
License-File: LICENSE
Requires-Dist: sepes >=0.12.0
